TaxslipsApiData/__init__.py
TaxslipsApiData-0.1.dist-info/LICENSE.txt
TaxslipsApiData-0.1.dist-info/METADATA
TaxslipsApiData-0.1.dist-info/WHEEL
TaxslipsApiData-0.1.dist-info/top_level.txt
TaxslipsApiData-0.1.dist-info/RECORD
