Metadata-Version: 2.1
Name: TaxslipsApiData
Version: 0.1
Summary: This is the package to store the test data
Home-page: UNKNOWN
Author: websentials
Author-email: ghayurbutt11@gmail.com
License: UNKNOWN
Platform: UNKNOWN
License-File: LICENSE.txt
